claude_mpm/BUILD_NUMBER
claude_mpm/VERSION
claude_mpm/__init__.py
claude_mpm/__main__.py
claude_mpm/constants.py
claude_mpm/init.py
claude_mpm/ticket_wrapper.py
claude_mpm/agents/BASE_AGENT.md
claude_mpm/agents/BASE_ENGINEER.md
claude_mpm/agents/CLAUDE_MPM_OUTPUT_STYLE.md
claude_mpm/agents/CLAUDE_MPM_RESEARCH_OUTPUT_STYLE.md
claude_mpm/agents/CLAUDE_MPM_TEACHER_OUTPUT_STYLE.md
claude_mpm/agents/MEMORY.md
claude_mpm/agents/PM_INSTRUCTIONS.md
claude_mpm/agents/WORKFLOW.md
claude_mpm/agents/__init__.py
claude_mpm/agents/agent-template.yaml
claude_mpm/agents/agent_loader.py
claude_mpm/agents/agent_loader_integration.py
claude_mpm/agents/agents_metadata.py
claude_mpm/agents/async_agent_loader.py
claude_mpm/agents/base_agent.json
claude_mpm/agents/frontmatter_validator.py
claude_mpm/agents/system_agent_config.py
claude_mpm/agents/templates/README.md
claude_mpm/agents/templates/__init__.py
claude_mpm/agents/templates/circuit-breakers.md
claude_mpm/agents/templates/context-management-examples.md
claude_mpm/agents/templates/git-file-tracking.md
claude_mpm/agents/templates/pm-examples.md
claude_mpm/agents/templates/pm-red-flags.md
claude_mpm/agents/templates/pr-workflow-examples.md
claude_mpm/agents/templates/research-gate-examples.md
claude_mpm/agents/templates/response-format.md
claude_mpm/agents/templates/structured-questions-examples.md
claude_mpm/agents/templates/ticket-completeness-examples.md
claude_mpm/agents/templates/ticketing-examples.md
claude_mpm/agents/templates/validation-templates.md
claude_mpm/auth/__init__.py
claude_mpm/auth/callback_server.py
claude_mpm/auth/models.py
claude_mpm/auth/oauth_manager.py
claude_mpm/auth/token_storage.py
claude_mpm/auth/providers/__init__.py
claude_mpm/auth/providers/base.py
claude_mpm/auth/providers/google.py
claude_mpm/cli/__init__.py
claude_mpm/cli/__main__.py
claude_mpm/cli/chrome_devtools_installer.py
claude_mpm/cli/executor.py
claude_mpm/cli/helpers.py
claude_mpm/cli/parser.py
claude_mpm/cli/startup.py
claude_mpm-5.6.101.dist-info/licenses/LICENSE
claude_mpm-5.6.101.dist-info/licenses/LICENSE-FAQ.md
claude_mpm-5.6.101.dist-info/METADATA
claude_mpm-5.6.101.dist-info/WHEEL
claude_mpm-5.6.101.dist-info/entry_points.txt
claude_mpm-5.6.101.dist-info/top_level.txt
claude_mpm-5.6.101.dist-info/RECORD
