Metadata-Version: 2.4
Name: claude-mpm
Version: 5.6.101
Summary: Claude Multi-Agent Project Manager - Orchestrate Claude with agent delegation and ticket tracking
Author-email: Bob Matsuoka <bob@matsuoka.com>
Maintainer: Claude MPM Team
License: Elastic-2.0
Project-URL: Homepage, https://github.com/bobmatnyc/claude-mpm
Project-URL: Repository, https://github.com/bobmatnyc/claude-mpm.git
Project-URL: Issues, https://github.com/bobmatnyc/claude-mpm/issues
Project-URL: Documentation, https://github.com/bobmatnyc/claude-mpm/blob/main/README.md
Keywords: claude,orchestration,multi-agent,ticket-management
Classifier: Development Status :: 3 - Alpha
Classifier: Intended Audience :: Developers
Classifier: License :: Other/Proprietary License
Classifier: Programming Language :: Python :: 3
Classifier: Programming Language :: Python :: 3.11
Classifier: Programming Language :: Python :: 3.12
Classifier: Programming Language :: Python :: 3.13
Requires-Python: >=3.11
License-File: LICENSE
License-File: LICENSE-FAQ.md
Requires-Dist: ai-trackdown-pytools>=1.4.0
Requires-Dist: pyyaml>=6.0
Requires-Dist: python-dotenv>=1.0.0
Requires-Dist: click>=8.0.0
Requires-Dist: pexpect>=4.8.0
Requires-Dist: psutil>=5.9.0
Requires-Dist: requests>=2.25.0
Requires-Dist: flask>=3.0.0
Requires-Dist: flask-cors>=4.0.0
Requires-Dist: watchdog>=3.0.0
Requires-Dist: python-socketio>=5.14.0
Requires-Dist: aiohttp>=3.9.0
Requires-Dist: aiohttp-cors<0.8.0,>=0.7.0
Requires-Dist: python-engineio>=4.8.0
Requires-Dist: aiofiles>=23.0.0
Requires-Dist: websockets>=12.0
Requires-Dist: python-frontmatter>=1.0.0
Requires-Dist: mistune>=3.0.0
Requires-Dist: tree-sitter>=0.21.0
Requires-Dist: ijson>=3.2.0
Requires-Dist: toml>=0.10.2
Requires-Dist: packaging>=21.0
Requires-Dist: pydantic>=2.0.0
Requires-Dist: pydantic-settings>=2.0.0
Requires-Dist: rich>=13.0.0
Requires-Dist: questionary>=2.0.0
Requires-Dist: pyee>=13.0.0
Requires-Dist: pathspec>=0.11.0
Requires-Dist: fastapi>=0.100.0
Requires-Dist: uvicorn>=0.20.0
Requires-Dist: httpx>=0.24.0
Requires-Dist: keyring>=24.0.0
Requires-Dist: cryptography>=41.0.0
Requires-Dist: mcp>=1.0.0
Provides-Extra: mcp
Requires-Dist: mcp>=0.1.0; extra == "mcp"
Requires-Dist: mcp-vector-search>=0.1.0; extra == "mcp"
Requires-Dist: mcp-browser>=0.1.0; extra == "mcp"
Requires-Dist: mcp-ticketer>=0.1.0; extra == "mcp"
Provides-Extra: dev
Requires-Dist: pytest>=7.0; extra == "dev"
Requires-Dist: pytest-asyncio; extra == "dev"
Requires-Dist: pytest-cov; extra == "dev"
Requires-Dist: ruff>=0.8.0; extra == "dev"
Requires-Dist: pylint>=3.0.0; extra == "dev"
Requires-Dist: pre-commit; extra == "dev"
Requires-Dist: mypy>=1.0.0; extra == "dev"
Requires-Dist: types-PyYAML>=6.0.0; extra == "dev"
Requires-Dist: types-requests>=2.25.0; extra == "dev"
Provides-Extra: eval
Requires-Dist: deepeval>=1.0.0; extra == "eval"
Requires-Dist: pytest>=7.4.0; extra == "eval"
Requires-Dist: pytest-asyncio>=0.21.0; extra == "eval"
Requires-Dist: pytest-timeout>=2.1.0; extra == "eval"
Provides-Extra: docs
Requires-Dist: sphinx>=7.2.0; extra == "docs"
Requires-Dist: sphinx-rtd-theme>=1.3.0; extra == "docs"
Requires-Dist: sphinx-autobuild>=2021.3.14; extra == "docs"
Provides-Extra: monitor
Requires-Dist: python-socketio>=5.14.0; extra == "monitor"
Requires-Dist: aiohttp>=3.9.0; extra == "monitor"
Requires-Dist: aiohttp-cors<0.8.0,>=0.7.0; extra == "monitor"
Requires-Dist: python-engineio>=4.8.0; extra == "monitor"
Requires-Dist: aiofiles>=23.0.0; extra == "monitor"
Requires-Dist: websockets>=12.0; extra == "monitor"
Provides-Extra: data-processing
Requires-Dist: pandas>=2.1.0; extra == "data-processing"
Requires-Dist: openpyxl>=3.1.0; extra == "data-processing"
Requires-Dist: xlsxwriter>=3.1.0; extra == "data-processing"
Requires-Dist: numpy>=1.24.0; extra == "data-processing"
Requires-Dist: pyarrow>=14.0.0; extra == "data-processing"
Requires-Dist: dask>=2023.12.0; extra == "data-processing"
Requires-Dist: polars>=0.19.0; extra == "data-processing"
Requires-Dist: xlrd>=2.0.0; extra == "data-processing"
Requires-Dist: xlwt>=1.3.0; extra == "data-processing"
Requires-Dist: csvkit>=1.3.0; extra == "data-processing"
Requires-Dist: tabulate>=0.9.0; extra == "data-processing"
Requires-Dist: python-dateutil>=2.8.0; extra == "data-processing"
Requires-Dist: lxml>=4.9.0; extra == "data-processing"
Requires-Dist: sqlalchemy>=2.0.0; extra == "data-processing"
Requires-Dist: psycopg2-binary>=2.9.0; extra == "data-processing"
Requires-Dist: pymongo>=4.5.0; extra == "data-processing"
Requires-Dist: redis>=5.0.0; extra == "data-processing"
Requires-Dist: beautifulsoup4>=4.12.0; extra == "data-processing"
Requires-Dist: jsonschema>=4.19.0; extra == "data-processing"
Provides-Extra: memory
Requires-Dist: kuzu-memory>=1.1.5; extra == "memory"
Provides-Extra: slack
Requires-Dist: slack-bolt>=1.18.0; extra == "slack"
Requires-Dist: slack-sdk>=3.23.0; extra == "slack"
Dynamic: license-file
